output_text_zeke/__init__.py
output_text_zeke/__main__.py
output_text_zeke-0.1.6.dist-info/LICENSE
output_text_zeke-0.1.6.dist-info/METADATA
output_text_zeke-0.1.6.dist-info/WHEEL
output_text_zeke-0.1.6.dist-info/entry_points.txt
output_text_zeke-0.1.6.dist-info/RECORD
